part_3/bin2bcd.v
////////////////////////////////////////////////////////////////////////////////////
// Copyright (c) 2012, Ameer M. Abdelhadi; ameer@ece.ubc.ca. All rights reserved. //
//                                                                                //
// Redistribution  and  use  in  source   and  binary  forms,   with  or  without //
// modification,  are permitted  provided that  the following conditions are met: //
//   * Redistributions   of  source   code  must  retain   the   above  copyright //
//     notice,  this   list   of   conditions   and   the  following  disclaimer. //
//   * Redistributions  in  binary  form  must  reproduce  the  above   copyright //
//     notice, this  list  of  conditions  and the  following  disclaimer in  the //
//     documentation and/or  other  materials  provided  with  the  distribution. //
//   * Neither the name of the University of British Columbia (UBC) nor the names //
//     of   its   contributors  may  be  used  to  endorse  or   promote products //
//     derived from  this  software without  specific  prior  written permission. //
//                                                                                //
// THIS  SOFTWARE IS  PROVIDED  BY THE COPYRIGHT HOLDERS AND CONTRIBUTORS "AS IS" //
// AND  ANY EXPRESS  OR IMPLIED WARRANTIES,  INCLUDING,  BUT NOT LIMITED TO,  THE //
// IMPLIED WARRANTIES OF MERCHANTABILITY AND FITNESS FOR A PARTICULAR PURPOSE ARE //
// DISCLAIMED.  IN NO  EVENT SHALL University of British Columbia (UBC) BE LIABLE //
// FOR ANY DIRECT,  INDIRECT,  INCIDENTAL,  SPECIAL,  EXEMPLARY, OR CONSEQUENTIAL //
// DAMAGES  (INCLUDING,  BUT NOT LIMITED TO,  PROCUREMENT OF  SUBSTITUTE GOODS OR //
// SERVICES;  LOSS OF USE,  DATA,  OR PROFITS;  OR BUSINESS INTERRUPTION) HOWEVER //
// CAUSED AND ON ANY THEORY OF LIABILITY,  WHETHER IN CONTRACT, STRICT LIABILITY, //
// OR TORT  (INCLUDING NEGLIGENCE OR OTHERWISE) ARISING IN ANY WAY OUT OF THE USE //
// OF  THIS SOFTWARE,  EVEN  IF  ADVISED  OF  THE  POSSIBILITY  OF  SUCH  DAMAGE. //
////////////////////////////////////////////////////////////////////////////////////

////////////////////////////////////////////////////////////////////////////////////
//                 bin2bcd.v:  Parametric  Binary to BCD Converter                // 
//                 Using Double Dabble / Shift and Add 3 Algorithm                //
//                                                                                //
// Ameer M.S. Abdelhadi (ameer@ece.ubc.ca; ameer.abdelhadi@gmail.com), Sept. 2012 //
////////////////////////////////////////////////////////////////////////////////////

////////////////////////////////////////////////////////////////////////////////////
//                                 18-bit Example                                 //
//                                                                                //
//                     B  B  B  B  B  B  B  B  B  B  B  B  B  B  B  B  B  B       //
//                     I  I  I  I  I  I  I  I  I  I  I  I  I  I  I  I  I  I       //
//                     N  N  N  N  N  N  N  N  N  N  N  N  N  N  N  N  N  N       //
//                     1  1  1  1  1  1  1  1  9  8  7  6  5  4  3  2  1  0       //
//     '0 '0 '0 '0 '0  7  6  5  4  3  2  1  0  |  |  |  |  |  |  |  |  |  |       //
//      |  |  |  |  |  |  |  |  |  |  |  |  |  |  |  |  |  |  |  |  |  |  |       //
//      |  |  |  |  V__V__V__V  |  |  |  |  |  |  |  |  |  |  |  |  |  |  |       //
//      |  |  |  | /IF>4THEN+3\ |  |  |  |  |  |  |  |  |  |  |  |  |  |  |       //
//      |  |  |  | \__________/ |  |  |  |  |  |  |  |  |  |  |  |  |  |  |       //
//      |  |  |  |  |  |  |  |  |  |  |  |  |  |  |  |  |  |  |  |  |  |  |       //
//      |  |  |  |  |  V__V__V__V  |  |  |  |  |  |  |  |  |  |  |  |  |  |       //
//      |  |  |  |  | /IF>4THEN+3\ |  |  |  |  |  |  |  |  |  |  |  |  |  |       //
//      |  |  |  |  | \__________/ |  |  |  |  |  |  |  |  |  |  |  |  |  |       //
//      |  |  |  |  |  |  |  |  |  |  |  |  |  |  |  |  |  |  |  |  |  |  |       //
//      |  |  |  |  |  |  V__V__V__V  |  |  |  |  |  |  |  |  |  |  |  |  |       //
//      |  |  |  |  |  | /IF>4THEN+3\ |  |  |  |  |  |  |  |  |  |  |  |  |       //
//      |  |  |  |  |  | \__________/ |  |  |  |  |  |  |  |  |  |  |  |  |       //
//      |  |  |  |  |  |  |  |  |  |  |  |  |  |  |  |  |  |  |  |  |  |  |       //
//      |  |  |  V__V__V__V  V__V__V__V  |  |  |  |  |  |  |  |  |  |  |  |       //
//      |  |  | /IF>4THEN+3\/IF>4THEN+3\ |  |  |  |  |  |  |  |  |  |  |  |       //
//      |  |  | \__________/\__________/ |  |  |  |  |  |  |  |  |  |  |  |       //
//      |  |  |  |  |  |  |  |  |  |  |  |  |  |  |  |  |  |  |  |  |  |  |       //
//      |  |  |  |  V__V__V__V  V__V__V__V  |  |  |  |  |  |  |  |  |  |  |       //
//      |  |  |  | /IF>4THEN+3\/IF>4THEN+3\ |  |  |  |  |  |  |  |  |  |  |       //
//      |  |  |  | \__________/\__________/ |  |  |  |  |  |  |  |  |  |  |       //
//      |  |  |  |  |  |  |  |  |  |  |  |  |  |  |  |  |  |  |  |  |  |  |       //
//      |  |  |  |  |  V__V__V__V  V__V__V__V  |  |  |  |  |  |  |  |  |  |       //
//      |  |  |  |  | /IF>4THEN+3\/IF>4THEN+3\ |  |  |  |  |  |  |  |  |  |       //
//      |  |  |  |  | \__________/\__________/ |  |  |  |  |  |  |  |  |  |       //
//      |  |  |  |  |  |  |  |  |  |  |  |  |  |  |  |  |  |  |  |  |  |  |       //
//      |  |  V__V__V__V  V__V__V__V  V__V__V__V  |  |  |  |  |  |  |  |  |       //
//      |  | /IF>4THEN+3\/IF>4THEN+3\/IF>4THEN+3\ |  |  |  |  |  |  |  |  |       //
//      |  | \__________/\__________/\__________/ |  |  |  |  |  |  |  |  |       //
//      |  |  |  |  |  |  |  |  |  |  |  |  |  |  |  |  |  |  |  |  |  |  |       //
//      |  |  |  V__V__V__V  V__V__V__V  V__V__V__V  |  |  |  |  |  |  |  |       //
//      |  |  | /IF>4THEN+3\/IF>4THEN+3\/IF>4THEN+3\ |  |  |  |  |  |  |  |       //
//      |  |  | \__________/\__________/\__________/ |  |  |  |  |  |  |  |       //
//      |  |  |  |  |  |  |  |  |  |  |  |  |  |  |  |  |  |  |  |  |  |  |       //
//      |  |  |  |  V__V__V__V  V__V__V__V  V__V__V__V  |  |  |  |  |  |  |       //
//      |  |  |  | /IF>4THEN+3\/IF>4THEN+3\/IF>4THEN+3\ |  |  |  |  |  |  |       //
//      |  |  |  | \__________/\__________/\__________/ |  |  |  |  |  |  |       //
//      |  |  |  |  |  |  |  |  |  |  |  |  |  |  |  |  |  |  |  |  |  |  |       //
//      |  V__V__V__V  V__V__V__V  V__V__V__V  V__V__V__V  |  |  |  |  |  |       //
//      | /IF>4THEN+3\/IF>4THEN+3\/IF>4THEN+3\/IF>4THEN+3\ |  |  |  |  |  |       //
//      | \__________/\__________/\__________/\__________/ |  |  |  |  |  |       //
//      |  |  |  |  |  |  |  |  |  |  |  |  |  |  |  |  |  |  |  |  |  |  |       //
//      |  |  V__V__V__V  V__V__V__V  V__V__V__V  V__V__V__V  |  |  |  |  |       //
//      |  | /IF>4THEN+3\/IF>4THEN+3\/IF>4THEN+3\/IF>4THEN+3\ |  |  |  |  |       //
//      |  | \__________/\__________/\__________/\__________/ |  |  |  |  |       //
//      |  |  |  |  |  |  |  |  |  |  |  |  |  |  |  |  |  |  |  |  |  |  |       //
//      |  |  |  V__V__V__V  V__V__V__V  V__V__V__V  V__V__V__V  |  |  |  |       //
//      |  |  | /IF>4THEN+3\/IF>4THEN+3\/IF>4THEN+3\/IF>4THEN+3\ |  |  |  |       //
//      |  |  | \__________/\__________/\__________/\__________/ |  |  |  |       //
//      |  |  |  |  |  |  |  |  |  |  |  |  |  |  |  |  |  |  |  |  |  |  |       //
//      V__V__V__V  V__V__V__V  V__V__V__V  V__V__V__V  V__V__V__V  |  |  |       //
//     /IF>4THEN+3\/IF>4THEN+3\/IF>4THEN+3\/IF>4THEN+3\/IF>4THEN+3\ |  |  |       //
//     \__________/\__________/\__________/\__________/\__________/ |  |  |       //
//      |  |  |  |  |  |  |  |  |  |  |  |  |  |  |  |  |  |  |  |  |  |  |       //
//      |  V__V__V__V  V__V__V__V  V__V__V__V  V__V__V__V  V__V__V__V  |  |       //
//      | /IF>4THEN+3\/IF>4THEN+3\/IF>4THEN+3\/IF>4THEN+3\/IF>4THEN+3\ |  |       //
//      | \__________/\__________/\__________/\__________/\__________/ |  |       //
//      |  |  |  |  |  |  |  |  |  |  |  |  |  |  |  |  |  |  |  |  |  |  |       //
//      |  |  V__V__V__V  V__V__V__V  V__V__V__V  V__V__V__V  V__V__V__V  |       //
//      |  | /IF>4THEN+3\/IF>4THEN+3\/IF>4THEN+3\/IF>4THEN+3\/IF>4THEN+3\ |       //
//      |  | \__________/\__________/\__________/\__________/\__________/ |       //
//      |  |  |  |  |  |  |  |  |  |  |  |  |  |  |  |  |  |  |  |  |  |  |       //
//      B  B  B  B  B  B  B  B  B  B  B  B  B  B  B  B  B  B  B  B  B  B  B       //
//      C  C  C  C  C  C  C  C  C  C  C  C  C  C  C  C  C  C  C  C  C  C  C       //
//      D  D  D  D  D  D  D  D  D  D  D  D  D  D  D  D  D  D  D  D  D  D  D       //
//      2  2  2  1  1  1  1  1  1  1  1  1  1  9  8  7  6  5  4  3  2  1  0       //
//      2  1  0  9  8  7  6  5  4  3  2  1  0                                     //
//     \_______/\__________/\__________/\__________/\__________/\__________/      //
//     100,000's  10,000's     1000's      100's        10's         1's          //
//                                                                                //
////////////////////////////////////////////////////////////////////////////////////

module bin2bcd #(
    parameter TCQ = 0.1,
    parameter W = 8 // input width
    )(
    input i_clk,
    input i_rstn,
    input [W - 1 : 0] i_bin,  // binary
    output [W + (W - 4) / 3 : 0] o_bcd
    ); // bcd {...,thousands,hundreds,tens,ones}

    reg [W - 1 : 0] bin_reg;
    reg [W + (W - 4) / 3 : 0] bcd_reg;
    
    integer i;
    integer j;

    // -------------------------------------------
    // ------------- Register Inputs -------------
    // -------------------------------------------

    always @(negedge i_clk) begin
        // synchronous active-low reset logic
        if(!i_rstn) begin
            bin_reg = #(TCQ) 0;
        end
        else begin
            bin_reg = i_bin;
        end
    end
    
    // -------------------------------------------
    // ---------- Calculate Result and -----------
    // ---------- Assign to a Register -----------
    // -------------------------------------------
    
    always @(negedge i_clk) begin
    
        // synchronous active-low reset logic
        if(!i_rstn) begin
            bcd_reg = #(TCQ) 0;
        end
        
        else begin
            
            for(i = 0; i <= W+(W-4)/3; i = i+1) begin
                bcd_reg[i] = 0; // initialize with zeros
            end
            
            bcd_reg[W-1:0] = bin_reg; // initialize with input vector
            
            for(i = 0; i <= W-4; i = i+1) begin // iterate on structure depth
                for(j = 0; j <= i/3; j = j+1) begin // iterate on structure width
                    if (bcd_reg[W-i+4*j -: 4] > 4) // if > 4
                        bcd_reg[W-i+4*j -: 4] = bcd_reg[W-i+4*j -: 4] + 4'd3; // add 3
                end
            end
        end
    end
    
    // -------------------------------------------
    // ---- Assign Registered Value to Output ----
    // -------------------------------------------
        
    assign o_bcd = bcd_reg;

endmodule

part_3/binary_to_bcd/sim_1/bin2bcd_tb.v
`timescale 1ns / 1ps
//////////////////////////////////////////////////////////////////////////////////
// Company: 
// Engineer: 
// 
// Create Date: 12/21/2023 12:45:21 PM
// Design Name: 
// Module Name: bin2bcd_tb
// Project Name: 
// Target Devices: 
// Tool Versions: 
// Description: 
// 
// Dependencies: 
// 
// Revision:
// Revision 0.01 - File Created
// Additional Comments:
// 
//////////////////////////////////////////////////////////////////////////////////

`define NUM_SEQUENCE 4

module bin2bcd_tb();
    
    parameter CLOCK_PULSE_WIDTH = 10;
    parameter TCQ = 0.1;
    parameter W = 4;
    
    reg i_clk = 1'b1;
    reg i_rstn = 1'b0;
    reg [W - 1 : 0] i_bin = 0;
    wire [W + (W - 4) / 3 : 0] o_bcd;
    reg [W - 1 : 0] bin = 0;
        
    reg [7:0] i = 0;
    
    // -------------------------------------------
    // ---------------- Dump VCD -----------------
    // -------------------------------------------
    
    initial begin
        $dumpfile("bin2bcd.vcd");
        $dumpvars(0);
    end
    
    // -------------------------------------------
    // ------------ DUT Instantiation ------------
    // -------------------------------------------
    
    bin2bcd#(
        .TCQ(TCQ),
        .W(W)
        ) bin2bcd_inst (
        .i_clk(i_clk),
        .i_rstn(i_rstn),
        .i_bin(i_bin),
        .o_bcd(o_bcd)
    ); 
    
    // -------------------------------------------
    // ------------- Generate Clock --------------
    // -------------------------------------------
    
    // generate clock signal
    always begin
        i_clk = ~i_clk;
        #CLOCK_PULSE_WIDTH;  
    end
    
    // -------------------------------------------
    // ---------------- Stimulus -----------------
    // -------------------------------------------
    
    initial begin : tb_block_main
        
        // do reset
        i_rstn <= 1'b0;
        #(2 * CLOCK_PULSE_WIDTH);
        i_rstn <=1'b1;
        
        for(i = 0; i < `NUM_SEQUENCE; i = i + 1) begin
            
            i_bin = {W{1'b1}} & {$random}%(2**W-1);
            //i_bin = bin;
            
            #(4 * CLOCK_PULSE_WIDTH)
            
            $display("-------------------------------------");
            $display("input_binary(DECIMAL) = %0d, output_BCD = %0b", i_bin, o_bcd);
            
        end
        
        $display("-------------------------------------");
        $display("Ali Abbasi, Derek Furtado");
        $display("ECE748@McMaster - Fall2023");
        $display("-------------------------------------");
        
        $finish;
        
    end
    
endmodule

part_3/binary_to_bcd/bin2bcd.vcd
$date
	Thu Dec 21 17:00:32 2023
$end

$version
	Synopsys VCS version T-2022.06-SP2_Full64
$end

$timescale
	1ps
$end

$comment Csum: 1 ca0c4dc8e4a9a722 $end


$scope module bin2bcd_tb $end
$var reg 1 ! i_clk $end
$var reg 1 " i_rstn $end
$var reg 4 # i_bin [3:0] $end
$var wire 5 $ o_bcd [4:0] $end
$var reg 4 % bin [3:0] $end
$var reg 8 & i [7:0] $end

$scope begin tb_block_main $end
$upscope $end


$scope module bin2bcd_inst $end
$var wire 1 ! i_clk $end
$var wire 1 " i_rstn $end
$var wire 4 # i_bin [3:0] $end
$var wire 5 $ o_bcd [4:0] $end
$var reg 4 ' bin_reg [3:0] $end
$var reg 5 $ bcd_reg [4:0] $end
$var integer 32 ( i $end
$var integer 32 ) j $end
$upscope $end

$upscope $end

$enddefinitions $end

#0
$dumpvars
0!
0"
bxxxxx $
b0000 %
bxxxxxxxxxxxxxxxxxxxxxxxxxxxxxxxx (
bxxxx '
b00000000 &
b0000 #
bxxxxxxxxxxxxxxxxxxxxxxxxxxxxxxxx )
$end
#100
b0000 '
b00000 $
#10000
1!
#20000
b1000 #
0!
1"
#30000
1!
#40000
0!
b1000 '
b01000 $
b00000000000000000000000000000001 (
b00000000000000000000000000000001 )
#50000
1!
#60000
b00000001 &
b1100 #
0!
b1100 '
b10010 $
#70000
1!
#80000
0!
#90000
1!
#100000
b00000010 &
b0111 #
0!
b0111 '
b00111 $
#110000
1!
#120000
0!
#130000
1!
#140000
b00000011 &
b0010 #
0!
b0010 '
b00010 $
#150000
1!
#160000
0!
#170000
1!
#180000
b00000100 &
